agents/__init__.py
agents/constrained_dqn.py
agents/constraints.py
envs/__init__.py
envs/wrappers.py
explainability/__init__.py
explainability/saliency.py
explainability/shap_explainer.py
saferl_lite-0.1.3.dist-info/licenses/LICENSE
saferl_lite-0.1.3.dist-info/METADATA
saferl_lite-0.1.3.dist-info/WHEEL
saferl_lite-0.1.3.dist-info/top_level.txt
saferl_lite-0.1.3.dist-info/RECORD
