Metadata-Version: 2.4
Name: saferl-lite
Version: 0.1.3
Summary: A lightweight, explainable, and constrained reinforcement learning toolkit.
Home-page: https://github.com/satyamcser/saferl-lite
Author: Satyam Mishra
Author-email: satyam@example.com
Project-URL: Documentation, https://github.com/satyamcser/saferl-lite/tree/main/docs
Project-URL: Source, https://github.com/satyamcser/saferl-lite
Project-URL: Bug Tracker, https://github.com/satyamcser/saferl-lite/issues
Classifier: Programming Language :: Python :: 3
Classifier: License :: OSI Approved :: MIT License
Classifier: Operating System :: OS Independent
Classifier: Intended Audience :: Science/Research
Classifier: Topic :: Scientific/Engineering :: Artificial Intelligence
Requires-Python: >=3.8
License-File: LICENSE
Requires-Dist: gym
Requires-Dist: gymnasium
Requires-Dist: numpy
Requires-Dist: torch
Requires-Dist: matplotlib
Requires-Dist: seaborn
Requires-Dist: pre-commit
Requires-Dist: flake8
Requires-Dist: pyyaml
Requires-Dist: shap
Requires-Dist: captum
Requires-Dist: typer
Requires-Dist: scikit-learn
Requires-Dist: pandas
Requires-Dist: pytest
Requires-Dist: pytest-cov
Requires-Dist: coverage
Requires-Dist: mkdocs
Requires-Dist: wandb
Requires-Dist: mkdocs>=1.5
Requires-Dist: mkdocs-material>=9.5
Requires-Dist: mkdocstrings[python]
Dynamic: author
Dynamic: author-email
Dynamic: classifier
Dynamic: description
Dynamic: description-content-type
Dynamic: home-page
Dynamic: license-file
Dynamic: project-url
Dynamic: requires-dist
Dynamic: requires-python
Dynamic: summary
